{
    "ADXMomentumEvaluator": false,
    "ATRVolatilityEvaluator": false,
    "BBMomentumEvaluator": false,
    "BBTrendEvaluator": false,
    "BTCTalkForumEvaluator": false,
    "CandleAnalysisTrendEvaluator": false,
    "ChaikinOscillatorMomentumEvaluator": false,
    "ChaikinVolatilityEvaluator": false,
    "DMITrendEvaluator": false,
    "DoubleMovingAverageTrendEvaluator": true,
    "EOMTrendEvaluator": false,
    "FullMixedStrategiesEvaluator": false,
    "GoogleTrendStatsEvaluator": false,
    "HighFrequencyStrategiesEvaluator": false,
    "InstantFluctuationsEvaluator": false,
    "InstantMAEvaluator": false,
    "InstantRegulatedMarketEvaluator": false,
    "InstantSocialReactionMixedStrategiesEvaluator": false,
    "InstantVolatilityEvaluator": false,
    "KlingerOscillatorMomentumEvaluator": false,
    "MACDMomentumEvaluator": false,
    "MarketStabilityStrategiesEvaluator": false,
    "MassIndexVolatilityEvaluator": false,
    "MediumNewsEvaluator": false,
    "MoveSignalsStrategyEvaluator": false,
    "OBVMomentumEvaluator": false,
    "RSIMomentumEvaluator": true,
    "RedditForumEvaluator": false,
    "SimpleMixedStrategiesEvaluator": true,
    "StochasticRSIVolatilityEvaluator": false,
    "StochasticVolatilityEvaluator": false,
    "TRIXMomentumEvaluator": false,
    "TwitterNewsEvaluator": false,
    "WhalesOrderBookEvaluator": false,
    "WilliamsRMomentumEvaluator": false
}
