{
  "crypto-currencies":{
    "Bitcoin": {
      "pairs" : ["BTC/USDT"]
    }
  },
  "exchanges": {
  },
  "services": {},
  "notification":{
    "global-info": true,
    "price-alerts": true,
    "trades": true,
    "notification-type": []
  },
  "trader":{
    "enabled": false,
    "risk": 0.5,
    "reference-market": "BTC",
    "mode": "DailyTradingMode"
  },
  "trader-simulator":{
    "enabled": true,
    "risk": 0.5,
    "starting-portfolio": {
      "BTC": 10,
      "USDT": 1000
    }
  }
}
